{
    "frames": [
        {
            "filename": "tile01",
            "frame": {
                "w": 200,
                "h": 148,
                "x": 0,
                "y": 0
            },
            "anchor": {
                "x": 0.5,
                "y": 0.5
            }
        },
        {
            "filename": "tile02",
            "frame": {
                "w": 200,
                "h": 148,
                "x": 200,
                "y": 0
            },
            "anchor": {
                "x": 0.5,
                "y": 0.5
            }
        },
        {
            "filename": "tile03",
            "frame": {
                "w": 200,
                "h": 148,
                "x": 400,
                "y": 0
            },
            "anchor": {
                "x": 0.5,
                "y": 0.5
            }
        },
        {
            "filename": "tile04",
            "frame": {
                "w": 200,
                "h": 148,
                "x": 600,
                "y": 0
            },
            "anchor": {
                "x": 0.5,
                "y": 0.5
            }
        },
        {
            "filename": "tile05",
            "frame": {
                "w": 200,
                "h": 148,
                "x": 800,
                "y": 0
            },
            "anchor": {
                "x": 0.5,
                "y": 0.5
            }
        },
        {
            "filename": "tile06",
            "frame": {
                "w": 200,
                "h": 148,
                "x": 1000,
                "y": 0
            },
            "anchor": {
                "x": 0.5,
                "y": 0.5
            }
        },
        {
            "filename": "tile07",
            "frame": {
                "w": 200,
                "h": 148,
                "x": 0,
                "y": 148
            },
            "anchor": {
                "x": 0.5,
                "y": 0.5
            }
        },
        {
            "filename": "tile08",
            "frame": {
                "w": 200,
                "h": 148,
                "x": 200,
                "y": 148
            },
            "anchor": {
                "x": 0.5,
                "y": 0.5
            }
        },
        {
            "filename": "tile09",
            "frame": {
                "w": 200,
                "h": 148,
                "x": 400,
                "y": 148
            },
            "anchor": {
                "x": 0.5,
                "y": 0.5
            }
        },
        {
            "filename": "tile10",
            "frame": {
                "w": 200,
                "h": 148,
                "x": 600,
                "y": 148
            },
            "anchor": {
                "x": 0.5,
                "y": 0.5
            }
        },
        {
            "filename": "tile11",
            "frame": {
                "w": 200,
                "h": 148,
                "x": 800,
                "y": 148
            },
            "anchor": {
                "x": 0.5,
                "y": 0.5
            }
        },
        {
            "filename": "tile12",
            "frame": {
                "w": 200,
                "h": 148,
                "x": 1000,
                "y": 148
            },
            "anchor": {
                "x": 0.5,
                "y": 0.5
            }
        },
        {
            "filename": "tile13",
            "frame": {
                "w": 200,
                "h": 148,
                "x": 0,
                "y": 296
            },
            "anchor": {
                "x": 0.5,
                "y": 0.5
            }
        },
        {
            "filename": "tile14",
            "frame": {
                "w": 200,
                "h": 148,
                "x": 200,
                "y": 296
            },
            "anchor": {
                "x": 0.5,
                "y": 0.5
            }
        },
        {
            "filename": "tile15",
            "frame": {
                "w": 200,
                "h": 148,
                "x": 400,
                "y": 296
            },
            "anchor": {
                "x": 0.5,
                "y": 0.5
            }
        },
        {
            "filename": "tile16",
            "frame": {
                "w": 200,
                "h": 148,
                "x": 600,
                "y": 296
            },
            "anchor": {
                "x": 0.5,
                "y": 0.5
            }
        },
        {
            "filename": "tile17",
            "frame": {
                "w": 200,
                "h": 148,
                "x": 800,
                "y": 296
            },
            "anchor": {
                "x": 0.5,
                "y": 0.5
            }
        },
        {
            "filename": "tile18",
            "frame": {
                "w": 200,
                "h": 148,
                "x": 1000,
                "y": 296
            },
            "anchor": {
                "x": 0.5,
                "y": 0.5
            }
        },
        {
            "filename": "tile19",
            "frame": {
                "w": 200,
                "h": 148,
                "x": 0,
                "y": 444
            },
            "anchor": {
                "x": 0.5,
                "y": 0.5
            }
        },
        {
            "filename": "tile20",
            "frame": {
                "w": 200,
                "h": 148,
                "x": 200,
                "y": 444
            },
            "anchor": {
                "x": 0.5,
                "y": 0.5
            }
        },
        {
            "filename": "tile21",
            "frame": {
                "w": 200,
                "h": 148,
                "x": 400,
                "y": 444
            },
            "anchor": {
                "x": 0.5,
                "y": 0.5
            }
        },
        {
            "filename": "tile22",
            "frame": {
                "w": 200,
                "h": 148,
                "x": 600,
                "y": 444
            },
            "anchor": {
                "x": 0.5,
                "y": 0.5
            }
        },
        {
            "filename": "tile23",
            "frame": {
                "w": 200,
                "h": 148,
                "x": 800,
                "y": 444
            },
            "anchor": {
                "x": 0.5,
                "y": 0.5
            }
        },
        {
            "filename": "tile24",
            "frame": {
                "w": 200,
                "h": 148,
                "x": 1000,
                "y": 444
            },
            "anchor": {
                "x": 0.5,
                "y": 0.5
            }
        },
        {
            "filename": "tile25",
            "frame": {
                "w": 200,
                "h": 148,
                "x": 0,
                "y": 592
            },
            "anchor": {
                "x": 0.5,
                "y": 0.5
            }
        },
        {
            "filename": "tile26",
            "frame": {
                "w": 200,
                "h": 148,
                "x": 200,
                "y": 592
            },
            "anchor": {
                "x": 0.5,
                "y": 0.5
            }
        },
        {
            "filename": "tile27",
            "frame": {
                "w": 200,
                "h": 148,
                "x": 400,
                "y": 592
            },
            "anchor": {
                "x": 0.5,
                "y": 0.5
            }
        },
        {
            "filename": "tile28",
            "frame": {
                "w": 200,
                "h": 148,
                "x": 600,
                "y": 592
            },
            "anchor": {
                "x": 0.5,
                "y": 0.5
            }
        },
        {
            "filename": "tile29",
            "frame": {
                "w": 200,
                "h": 148,
                "x": 800,
                "y": 592
            },
            "anchor": {
                "x": 0.5,
                "y": 0.5
            }
        },
        {
            "filename": "tile30",
            "frame": {
                "w": 200,
                "h": 148,
                "x": 1000,
                "y": 592
            },
            "anchor": {
                "x": 0.5,
                "y": 0.5
            }
        },
        {
            "filename": "tile31",
            "frame": {
                "w": 200,
                "h": 148,
                "x": 0,
                "y": 740
            },
            "anchor": {
                "x": 0.5,
                "y": 0.5
            }
        },
        {
            "filename": "tile32",
            "frame": {
                "w": 200,
                "h": 148,
                "x": 200,
                "y": 740
            },
            "anchor": {
                "x": 0.5,
                "y": 0.5
            }
        },
        {
            "filename": "tile33",
            "frame": {
                "w": 200,
                "h": 148,
                "x": 400,
                "y": 740
            },
            "anchor": {
                "x": 0.5,
                "y": 0.5
            }
        },
        {
            "filename": "tile34",
            "frame": {
                "w": 200,
                "h": 148,
                "x": 600,
                "y": 740
            },
            "anchor": {
                "x": 0.5,
                "y": 0.5
            }
        },
        {
            "filename": "tile35",
            "frame": {
                "w": 200,
                "h": 148,
                "x": 800,
                "y": 740
            },
            "anchor": {
                "x": 0.5,
                "y": 0.5
            }
        },
        {
            "filename": "tile36",
            "frame": {
                "w": 200,
                "h": 148,
                "x": 1000,
                "y": 740
            },
            "anchor": {
                "x": 0.5,
                "y": 0.5
            }
        }
    ],
    "meta": {
        "description": "Atlas generado con Atlas Packer Gamma V2",
        "web": "https://gammafp.github.io/atlas-packer-phaser/"
    }
}